cmsplugin_articles_ai/__init__.py
cmsplugin_articles_ai/admin.py
cmsplugin_articles_ai/apps.py
cmsplugin_articles_ai/article_urls.py
cmsplugin_articles_ai/cms_apps.py
cmsplugin_articles_ai/cms_plugins.py
cmsplugin_articles_ai/factories.py
cmsplugin_articles_ai/views.py
cmsplugin_articles_ai/__pycache__/__init__.cpython-35.pyc
cmsplugin_articles_ai/__pycache__/admin.cpython-35.pyc
cmsplugin_articles_ai/__pycache__/apps.cpython-35.pyc
cmsplugin_articles_ai/__pycache__/article_urls.cpython-35.pyc
cmsplugin_articles_ai/__pycache__/cms_apps.cpython-35.pyc
cmsplugin_articles_ai/__pycache__/cms_plugins.cpython-35.pyc
cmsplugin_articles_ai/__pycache__/factories.cpython-35.pyc
cmsplugin_articles_ai/__pycache__/views.cpython-35.pyc
cmsplugin_articles_ai/management/__init__.py
cmsplugin_articles_ai/management/__pycache__/__init__.cpython-35.pyc
cmsplugin_articles_ai/management/commands/__init__.py
cmsplugin_articles_ai/management/commands/publish_test_articles.py
cmsplugin_articles_ai/management/commands/__pycache__/__init__.cpython-35.pyc
cmsplugin_articles_ai/management/commands/__pycache__/publish_test_articles.cpython-35.pyc
cmsplugin_articles_ai/migrations/0001_initial.py
cmsplugin_articles_ai/migrations/0002_add_language_fields.py
cmsplugin_articles_ai/migrations/0003_add_non_unique_slug_to_tags.py
cmsplugin_articles_ai/migrations/0004_data_migration_for_slug_field.py
cmsplugin_articles_ai/migrations/0005_make_tag_slug_field_unique.py
cmsplugin_articles_ai/migrations/0006_add_publisher_support.py
cmsplugin_articles_ai/migrations/0007_add_lead_paragraph_and_permissions.py
cmsplugin_articles_ai/migrations/0008_categories.py
cmsplugin_articles_ai/migrations/0009_auto_20170919_0918.py
cmsplugin_articles_ai/migrations/0010_do_not_require_exclude_tags.py
cmsplugin_articles_ai/migrations/__init__.py
cmsplugin_articles_ai/migrations/__pycache__/0001_initial.cpython-35.pyc
cmsplugin_articles_ai-0.2.4.dist-info/DESCRIPTION.rst
cmsplugin_articles_ai-0.2.4.dist-info/METADATA
cmsplugin_articles_ai-0.2.4.dist-info/RECORD
cmsplugin_articles_ai-0.2.4.dist-info/WHEEL
cmsplugin_articles_ai-0.2.4.dist-info/metadata.json
cmsplugin_articles_ai-0.2.4.dist-info/top_level.txt
