Metadata-Version: 2.0
Name: cmsplugin-articles-ai
Version: 0.2.4
Summary: Articles management app for Django CMS
Home-page: https://github.com/andersinno/cmsplugin-articles-ai
Author: Anders Innovations
Author-email: info@anders.fi
License: MIT
Platform: UNKNOWN
Requires-Dist: django-cms (>=3.2,<3.5)
Requires-Dist: django-enumfields (>=0.8.0)
Requires-Dist: django-filer (>=1.2.4)
Requires-Dist: django-soft-choice-fields (>=0.3.1)
Requires-Dist: djangocms-text-ckeditor (>=3.0.0)
Requires-Dist: easy-thumbnails (>=2.3)
Requires-Dist: django-model-publisher-ai (>=0.3.1)
Provides-Extra: utils
Requires-Dist: factory-boy (>=0.6.0); extra == 'utils'
